bin/__init__.py
hammr/__init__.py
hammr/hammr.py
hammr/commands/__init__.py
hammr/commands/account/__init__.py
hammr/commands/account/account.py
hammr/commands/bundle/__init__.py
hammr/commands/bundle/bundle.py
hammr/commands/deploy/__init__.py
hammr/commands/deploy/deploy.py
hammr/commands/format/__init__.py
hammr/commands/format/format.py
hammr/commands/image/__init__.py
hammr/commands/image/image.py
hammr/commands/migration/__init__.py
hammr/commands/migration/migration.py
hammr/commands/os/__init__.py
hammr/commands/os/os.py
hammr/commands/platform/__init__.py
hammr/commands/platform/platform.py
hammr/commands/quota/__init__.py
hammr/commands/quota/quota.py
hammr/commands/scan/__init__.py
hammr/commands/scan/scan.py
hammr/commands/template/__init__.py
hammr/commands/template/template.py
hammr/commands/user/__init__.py
hammr/commands/user/user.py
hammr/utils/__init__.py
hammr/utils/account_utils.py
hammr/utils/bundle_utils.py
hammr/utils/constants.py
hammr/utils/credentials.py
hammr/utils/deployment_utils.py
hammr/utils/generate_utils.py
hammr/utils/hammr_utils.py
hammr/utils/image_utils.py
hammr/utils/migration_utils.py
hammr/utils/publish_builders.py
hammr/utils/publish_utils.py
hammr/utils/scan_utils.py
hammr-3.8.13.data/scripts/hammr
hammr-3.8.13.data/scripts/hammr.bat
hammr-3.8.13.dist-info/DESCRIPTION.rst
hammr-3.8.13.dist-info/METADATA
hammr-3.8.13.dist-info/RECORD
hammr-3.8.13.dist-info/WHEEL
hammr-3.8.13.dist-info/metadata.json
hammr-3.8.13.dist-info/top_level.txt
tests/__init__.py
tests/unit/__init__.py
tests/unit/commands/__init__.py
tests/unit/commands/deploy/__init__.py
tests/unit/commands/deploy/test_deploy_list.py
tests/unit/commands/image/__init__.py
tests/unit/commands/image/deploy_test_utils.py
tests/unit/commands/image/info_test_utils.py
tests/unit/commands/image/test_deploy_aws.py
tests/unit/commands/image/test_deploy_azure.py
tests/unit/commands/image/test_deploy_openstack.py
tests/unit/commands/image/test_image.py
tests/unit/commands/scan/__init__.py
tests/unit/commands/scan/test_scan.py
tests/unit/commands/template/__init__.py
tests/unit/commands/template/test_template.py
