Metadata-Version: 2.0
Name: hammr
Version: 3.8.13
Summary: Command-line tool for building conistent and repeatable machine images for multiple cloud platforms
Home-page: http://hammr.io
Author: Joris Bremond
Author-email: joris.bremond@usharesoft.com
License: Apache License 2.0
Platform: UNKNOWN
Classifier: Development Status :: 4 - Beta
Classifier: Environment :: Console
Classifier: Intended Audience :: Developers
Classifier: Intended Audience :: System Administrators
Classifier: Natural Language :: English
Classifier: Operating System :: MacOS :: MacOS X
Classifier: Operating System :: Microsoft :: Windows
Classifier: Operating System :: POSIX
Classifier: License :: OSI Approved :: Apache Software License
Classifier: Programming Language :: Python
Classifier: Programming Language :: Python :: 2.7
Requires-Dist: uforge-python-sdk (==3.8.13)
Requires-Dist: httplib2 (==0.9)
Requires-Dist: texttable (==0.8.1)
Requires-Dist: progressbar (==2.3)
Requires-Dist: argparse
Requires-Dist: paramiko (==1.12)
Requires-Dist: pyparsing (==2.0.2)
Requires-Dist: pyyaml (==3.12)
Requires-Dist: hurry.filesize (==0.9)
Requires-Dist: termcolor (==1.1.0)
Requires-Dist: junit-xml (==1.3)
Requires-Dist: xmlrunner (==1.7.7)
Requires-Dist: ussclicore (==1.0.11)
